soleil/__init__.py
soleil/_utils.py
soleil/package.py
soleil/rcall.py
soleil/rstr.py
soleil/solconf.py
soleil/utils.py
soleil/cli_tools/__init__.py
soleil/cli_tools/_argparse_patches.py
soleil/cli_tools/solconfarg.py
soleil/cli_tools/solex_decorator.py
soleil/loader/__init__.py
soleil/loader/loader.py
soleil/loader/pre_processor.py
soleil/overrides/__init__.py
soleil/overrides/overridable.py
soleil/overrides/overrides.py
soleil/overrides/parser.py
soleil/overrides/req.py
soleil/overrides/variable_path.py
soleil/resolvers/__init__.py
soleil/resolvers/base.py
soleil/resolvers/class_resolver.py
soleil/resolvers/modifiers.py
soleil/resolvers/module_resolver.py
soleil/special/__init__.py
soleil/special/resolved.py
soleil-0.1.1.data/scripts/solex
soleil-0.1.1.dist-info/LICENSE
soleil-0.1.1.dist-info/METADATA
soleil-0.1.1.dist-info/WHEEL
soleil-0.1.1.dist-info/top_level.txt
soleil-0.1.1.dist-info/RECORD
