Metadata-Version: 2.1
Name: soleil
Version: 0.1.1
Summary: Object configuration system
Home-page: https://github.com/zepedaj/soleil
Author: Joaquin Zepeda
Author-email: Joaquin Zepeda <jazs.pro@gmail.com>
Project-URL: Homepage, https://github.com/zepedaj/soleil
Project-URL: Issues, https://github.com/zepedaj/soleil/issues
Project-URL: Documentation, https://soleil.readthedocs.io/en/latest/
Keywords: configuration,Machine Learning,object oriented
Classifier: Programming Language :: Python :: 3
Classifier: License :: OSI Approved :: MIT License
Classifier: Operating System :: OS Independent
Requires-Python: >=3.8
License-File: LICENSE
Requires-Dist: jztools
Requires-Dist: climax
Requires-Dist: rich
Requires-Dist: freezegun
